ergo_angle/ErgoEval.py
ergo_angle/ErgoUtils.py
ergo_angle/__init__.py
ergo_angle/config.py
ergo_angle-0.1.0.dist-info/LICENSE
ergo_angle-0.1.0.dist-info/METADATA
ergo_angle-0.1.0.dist-info/WHEEL
ergo_angle-0.1.0.dist-info/top_level.txt
ergo_angle-0.1.0.dist-info/RECORD
